iminfra/__init__.py
iminfra/cli/__init__.py
iminfra/cli/main.py
iminfra-0.1.0.dist-info/entry_points.txt
iminfra-0.1.0.dist-info/WHEEL
iminfra-0.1.0.dist-info/METADATA
iminfra-0.1.0.dist-info/RECORD
